pypkgtemp/__init__.py
pypkgtemp/__main__.py
pypkgtemp/hello.py
pypkgtemp-1.2.0.dist-info/DESCRIPTION.rst
pypkgtemp-1.2.0.dist-info/METADATA
pypkgtemp-1.2.0.dist-info/RECORD
pypkgtemp-1.2.0.dist-info/WHEEL
pypkgtemp-1.2.0.dist-info/entry_points.txt
pypkgtemp-1.2.0.dist-info/metadata.json
pypkgtemp-1.2.0.dist-info/top_level.txt
