Metadata-Version: 2.0
Name: pypkgtemp
Version: 1.2.0
Summary: A python package template
Home-page: https://gitlab.com/costrouc/knoxpy-sqlite-pypi-readthedocs
Author: Chris Ostrouchov
Author-email: chris.ostrouchov+pypkgtemp@gmail.com
License: MIT
Keywords: python package template documentation testing continuous deployment
Platform: UNKNOWN
Classifier: Development Status :: 3 - Alpha
Classifier: Natural Language :: English
Classifier: License :: OSI Approved :: MIT License
Classifier: Programming Language :: Python :: 3.6
